{"Jo Koy": {"title": "TV News Roundup: Netflix Releases Trailer for Jo Koy\u2019s New Comedy Special (Watch)", "body": "The special, titled \u201cJo Koy: In His Elements,\u201c features Koy performing in the Philippines alongside other Filipino American performers. It premieres on the streamer...", "date": "6 days ago", "link": "google.com/url?q=https://variety.com/2020/tv/news/tv-roundup-jo-koy-special-trailer-1234617750/&sa=U&ved=2ahUKEwjR7YiY5ebpAhXZGDQIHf_DCJUQxfQBMAB6BAgGEAE&usg=AOvVaw14mnf1Ttj4Wu-1RYh-rM5V"}}